napari_plot/__init__.py
napari_plot/_dock_widget.py
napari_plot/_version.py
napari_plot/conftest.py
napari_plot/viewer.py
napari_plot/window.py
napari_plot/_qt/__init__.py
napari_plot/_qt/helpers.py
napari_plot/_qt/qt_dialog.py
napari_plot/_qt/qt_event_loop.py
napari_plot/_qt/qt_layer_buttons.py
napari_plot/_qt/qt_main_window.py
napari_plot/_qt/qt_toolbar.py
napari_plot/_qt/qt_viewer.py
napari_plot/_qt/_tests/__init__.py
napari_plot/_qt/_tests/test_icon_button.py
napari_plot/_qt/_tests/test_icon_label.py
napari_plot/_qt/_tests/test_qt_viewer.py
napari_plot/_qt/_tests/test_qt_window.py
napari_plot/_qt/layer_controls/__init__.py
napari_plot/_qt/layer_controls/qt_axis_controls.py
napari_plot/_qt/layer_controls/qt_camera_controls.py
napari_plot/_qt/layer_controls/qt_centroids_controls.py
napari_plot/_qt/layer_controls/qt_infline_controls.py
napari_plot/_qt/layer_controls/qt_layer_controls_base.py
napari_plot/_qt/layer_controls/qt_layer_controls_container.py
napari_plot/_qt/layer_controls/qt_layers_dialog.py
napari_plot/_qt/layer_controls/qt_line_controls.py
napari_plot/_qt/layer_controls/qt_multiline_controls.py
napari_plot/_qt/layer_controls/qt_region_controls.py
napari_plot/_qt/layer_controls/qt_scatter_controls.py
napari_plot/_qt/layer_controls/_tests/__init__.py
napari_plot/_qt/layer_controls/_tests/test_qt_infline_controls.py
napari_plot/_qt/layer_controls/_tests/test_qt_line_controls.py
napari_plot/_qt/layer_controls/_tests/test_qt_multiline_controls.py
napari_plot/_qt/layer_controls/_tests/test_qt_region_controls.py
napari_plot/_qt/layer_controls/_tests/test_qt_scatter_controls.py
napari_plot/_qt/widgets/__init__.py
napari_plot/_qt/widgets/qt_icon_button.py
napari_plot/_qt/widgets/qt_icon_label.py
napari_plot/_qt/widgets/qt_line.py
napari_plot/_qt/widgets/qt_mini_toolbar.py
napari_plot/_tests/__init__.py
napari_plot/_tests/test_dock_widget.py
napari_plot/_tests/test_examples.py
napari_plot/_tests/utils.py
napari_plot/_vispy/__init__.py
napari_plot-0.1.5.dist-info/LICENSE
napari_plot-0.1.5.dist-info/METADATA
napari_plot-0.1.5.dist-info/WHEEL
napari_plot-0.1.5.dist-info/entry_points.txt
napari_plot-0.1.5.dist-info/top_level.txt
napari_plot-0.1.5.dist-info/RECORD
