Metadata-Version: 2.1
Name: napari-plot
Version: 0.1.5
Summary: Plugin providing support for 1d plotting in napari.
Home-page: https://github.com/lukasz-migas/napari-1d
Author: Lukasz G. Migas
Author-email: lukas.migas@yahoo.com
License: BSD-3
Project-URL: Bug Tracker, https://github.com/lukasz-migas/napari-1d/issues
Project-URL: Documentation, https://github.com/lukasz-migas/napari-1d#README.md
Project-URL: Source Code, https://github.com/lukasz-migas/napari-1d
Project-URL: User Support, https://github.com/lukasz-migas/napari-1d/issues
Platform: UNKNOWN
Classifier: Development Status :: 2 - Pre-Alpha
Classifier: Intended Audience :: Developers
Classifier: Framework :: napari
Classifier: Topic :: Software Development :: Testing
Classifier: Programming Language :: Python
Classifier: Programming Language :: Python :: 3
Classifier: Programming Language :: Python :: 3.7
Classifier: Programming Language :: Python :: 3.8
Classifier: Programming Language :: Python :: 3.9
Classifier: Operating System :: OS Independent
Classifier: License :: OSI Approved :: BSD License
Requires-Python: >=3.7
License-File: LICENSE
Requires-Dist: napari-plugin-engine (>=0.1.4)
Requires-Dist: numpy
Requires-Dist: qtpy
Requires-Dist: qtawesome
Requires-Dist: napari (<0.4.15,>=0.4.13)
Requires-Dist: matplotlib
Requires-Dist: vispy (>=0.9.6)
Provides-Extra: all
Requires-Dist: PySide2 (!=5.15.0,>=5.13.2) ; extra == 'all'
Provides-Extra: dev
Requires-Dist: pre-commit (>=2.9.0) ; extra == 'dev'
Requires-Dist: black (==22.1.0) ; extra == 'dev'
Requires-Dist: flake8 (==4.0.1) ; extra == 'dev'
Requires-Dist: PySide2 (!=5.15.0,>=5.13.2) ; extra == 'dev'
Requires-Dist: pytest ; extra == 'dev'
Requires-Dist: pytest-qt ; extra == 'dev'
Requires-Dist: scikit-image ; extra == 'dev'
Provides-Extra: pyqt
Requires-Dist: PyQt5 (!=5.15.0,>=5.12.3) ; extra == 'pyqt'
Provides-Extra: pyqt5
Requires-Dist: PyQt5 (!=5.15.0,>=5.12.3) ; extra == 'pyqt5'
Provides-Extra: pyside
Requires-Dist: PySide2 (!=5.15.0,>=5.13.2) ; extra == 'pyside'
Provides-Extra: pyside2
Requires-Dist: PySide2 (!=5.15.0,>=5.13.2) ; extra == 'pyside2'
Provides-Extra: qt
Requires-Dist: PyQt5 (!=5.15.0,>=5.12.3) ; extra == 'qt'
Provides-Extra: testing
Requires-Dist: pytest ; extra == 'testing'
Requires-Dist: pytest-qt ; extra == 'testing'
Requires-Dist: scikit-image ; extra == 'testing'
